upt_openbsd/__init__.py
upt_openbsd/upt_openbsd.py
upt_openbsd/templates/base.mk
upt_openbsd/templates/perl.mk
upt_openbsd/templates/python.mk
upt_openbsd/templates/ruby.mk
upt_openbsd/tests/__init__.py
upt_openbsd/tests/test_openbsd_backend.py
upt_openbsd/tests/test_openbsd_package.py
upt_openbsd/tests/test_perl_package.py
upt_openbsd/tests/test_python_package.py
upt_openbsd/tests/test_ruby_package.py
upt_openbsd-0.5.dist-info/LICENSE
upt_openbsd-0.5.dist-info/METADATA
upt_openbsd-0.5.dist-info/WHEEL
upt_openbsd-0.5.dist-info/entry_points.txt
upt_openbsd-0.5.dist-info/top_level.txt
upt_openbsd-0.5.dist-info/RECORD
