Metadata-Version: 2.1
Name: upt-openbsd
Version: 0.5
Summary: OpenBSD backend for upt
Home-page: https://framagit.org/upt/upt-openbsd
Author: Cyril Roelandt
Author-email: tipecaml@gmail.com
License: UNKNOWN
Platform: UNKNOWN
Classifier: Development Status :: 3 - Alpha
Classifier: License :: OSI Approved :: BSD License
Classifier: Programming Language :: Python :: 3
Classifier: Programming Language :: Python :: 3.6
Requires-Dist: jinja2
Requires-Dist: upt (>=0.7)
